dbt_pumpkin/__init__.py
dbt_pumpkin/cli.py
dbt_pumpkin/data.py
dbt_pumpkin/dbt_compat.py
dbt_pumpkin/exception.py
dbt_pumpkin/loader.py
dbt_pumpkin/params.py
dbt_pumpkin/plan.py
dbt_pumpkin/planner.py
dbt_pumpkin/pumpkin.py
dbt_pumpkin/resolver.py
dbt_pumpkin/storage.py
dbt_pumpkin/version.py
dbt_pumpkin/macros/detect_case_folding.sql
dbt_pumpkin/macros/lookup_tables.sql
dbt_pumpkin-0.4.1.dist-info/METADATA
dbt_pumpkin-0.4.1.dist-info/WHEEL
dbt_pumpkin-0.4.1.dist-info/entry_points.txt
dbt_pumpkin-0.4.1.dist-info/licenses/LICENSE
dbt_pumpkin-0.4.1.dist-info/RECORD
