Metadata-Version: 2.4
Name: dbt-pumpkin
Version: 0.4.1
Project-URL: Source code, https://github.com/kokorin/dbt-pumpkin
Author-email: Denis Kokorin <kokorin86@gmail.com>
License-Expression: Apache-2.0
License-File: LICENSE
Requires-Python: >=3.9
Requires-Dist: click>=8.1.0
Requires-Dist: ruamel-yaml>=0.17
